bk_monitor_report/__init__.py
bk_monitor_report/__version__.py
bk_monitor_report/contrib/__init__.py
bk_monitor_report/contrib/celery.py
bk_monitor_report/reporter.py
bk_monitor_report-1.2.1.dist-info/LICENSE.txt
bk_monitor_report-1.2.1.dist-info/WHEEL
bk_monitor_report-1.2.1.dist-info/METADATA
bk_monitor_report-1.2.1.dist-info/RECORD
