Metadata-Version: 2.1
Name: bk-monitor-report
Version: 1.2.1
Summary: custom reporter python sdk for bk-monitor
License: MIT
Author: homholueng
Author-email: homholueng@gmail.com
Requires-Python: >=3.6.0,<4.0.0
Classifier: License :: OSI Approved :: MIT License
Classifier: Programming Language :: Python :: 3
Classifier: Programming Language :: Python :: 3.10
Classifier: Programming Language :: Python :: 3.6
Classifier: Programming Language :: Python :: 3.7
Classifier: Programming Language :: Python :: 3.8
Classifier: Programming Language :: Python :: 3.9
Requires-Dist: prometheus-client (>=0.9.0,<0.10.0)
Requires-Dist: requests (>=2.20.0,<3.0.0)
